doki-net/__init__.py
doki-net/ann/__init__.py
doki-net/ann/backprop.py
doki-net/ann/executor.py
doki-net/ann/networkGenerator.py
doki-net/ann/nodes/__init__.py
doki-net/ann/nodes/identity.py
doki-net/ann/nodes/relu.py
doki-net/ann/nodes/sigmoid.py
doki-net/ann/nodes/tanh.py
doki-net/ann/nodes/type.py
doki-net/cnn/__init__.py
doki-net/examples/__init__.py
doki-net/examples/ann-example-backprop-1.py
doki-net/examples/ann-example-execute-1.py
doki-net/examples/ann-example-execute-2.py
doki-net/examples/ann-example-network-gen-1.py
doki-net/examples/ann-example-network-gen-2.py
doki-net/examples/ann-example-network-gen-3.py
doki-net/examples/rnn-example-backprop-1.py
doki-net/examples/rnn-example-execute-1.py
doki-net/rnn/__init__.py
doki-net/rnn/backpropThroughTime.py
doki-net/rnn/executor.py
doki-net/rnn/networkGenerator.py
doki-net/rnn/nodes/__init__.py
doki-net/rnn/nodes/identity.py
doki-net/rnn/nodes/relu.py
doki-net/rnn/nodes/sigmoid.py
doki-net/rnn/nodes/tanh.py
doki-net/rnn/nodes/type.py
doki_net/__init__.py
doki_net/ann/__init__.py
doki_net/ann/backprop.py
doki_net/ann/executor.py
doki_net/ann/networkGenerator.py
doki_net/ann/nodes/__init__.py
doki_net/ann/nodes/identity.py
doki_net/ann/nodes/relu.py
doki_net/ann/nodes/sigmoid.py
doki_net/ann/nodes/tanh.py
doki_net/ann/nodes/type.py
doki_net/cnn/__init__.py
doki_net/examples/__init__.py
doki_net/examples/ann-example-backprop-1.py
doki_net/examples/ann-example-execute-1.py
doki_net/examples/ann-example-execute-2.py
doki_net/examples/ann-example-network-gen-1.py
doki_net/examples/ann-example-network-gen-2.py
doki_net/examples/ann-example-network-gen-3.py
doki_net/examples/rnn-example-backprop-1.py
doki_net/examples/rnn-example-execute-1.py
doki_net/rnn/__init__.py
doki_net/rnn/backpropThroughTime.py
doki_net/rnn/executor.py
doki_net/rnn/networkGenerator.py
doki_net/rnn/nodes/__init__.py
doki_net/rnn/nodes/identity.py
doki_net/rnn/nodes/relu.py
doki_net/rnn/nodes/sigmoid.py
doki_net/rnn/nodes/tanh.py
doki_net-0.2.0.1.dist-info/LICENSE
doki_net-0.2.0.1.dist-info/METADATA
doki_net-0.2.0.1.dist-info/WHEEL
doki_net-0.2.0.1.dist-info/top_level.txt
doki_net-0.2.0.1.dist-info/RECORD
