Metadata-Version: 2.1
Name: doki-net
Version: 0.2.0.1
Summary: A standard neural network implementation
Home-page: https://github.com/doki-net/doki-net
Author: Oliver Fallows
Author-email: ollyfallows@outlook.com
License: UNKNOWN
Platform: UNKNOWN
Classifier: Programming Language :: Python :: 3
Classifier: License :: OSI Approved :: GNU General Public License v3 or later (GPLv3+)
Classifier: Operating System :: OS Independent
